envisionhgdetector/__init__.py
envisionhgdetector/config.py
envisionhgdetector/demo_webcam_realtime.py
envisionhgdetector/detector.py
envisionhgdetector/model.py
envisionhgdetector/model_cnn.py
envisionhgdetector/model_lightgbm.py
envisionhgdetector/preprocessing.py
envisionhgdetector/test_config.py
envisionhgdetector/utils.py
envisionhgdetector/dashboard/app.py
envisionhgdetector/model/lightgbm_gesture_model_v1.pkl
envisionhgdetector/model/model_weights_20250224_103340.h5
envisionhgdetector-2.0.0.9.dist-info/LICENSE
envisionhgdetector-2.0.0.9.dist-info/METADATA
envisionhgdetector-2.0.0.9.dist-info/WHEEL
envisionhgdetector-2.0.0.9.dist-info/top_level.txt
envisionhgdetector-2.0.0.9.dist-info/RECORD
