Metadata-Version: 2.1
Name: envisionhgdetector
Version: 2.0.0.9
Summary: Hand gesture detection using MediaPipe and CNN, kinematic analysis, and visualization.
Home-page: https://github.com/wimpouw/envisionhgdetector
Author: Wim Pouw, Bosco Yung, Sharjeel Shaikh, James Trujillo, Antonio Rueda-Toicen, Gerard de Melo, Babajide Owoyele
Author-email: wim.pouw@donders.ru.nl
Classifier: Programming Language :: Python :: 3
Classifier: License :: OSI Approved :: MIT License
Classifier: Operating System :: OS Independent
Classifier: Topic :: Scientific/Engineering :: Artificial Intelligence
Classifier: Topic :: Scientific/Engineering :: Image Recognition
Requires-Python: >=3.7
License-File: LICENSE
Requires-Dist: moviepy==2.1.1
Requires-Dist: protobuf<4,>=3.11
Requires-Dist: numpy<2.0.0,>=1.21.0
Requires-Dist: opencv-python>=4.7.0.72
Requires-Dist: tensorflow-cpu==2.15.1
Requires-Dist: mediapipe==0.10.7
Requires-Dist: pandas<2.0.0,>=1.5.0
Requires-Dist: pytest>=7.0.0
Requires-Dist: black>=22.0.0
Requires-Dist: tqdm<5.0.0,>=4.65.0
Requires-Dist: shapedtw==1.0.3
Requires-Dist: umap-learn==0.5.3
Requires-Dist: scipy>=1.10.0
Requires-Dist: dash==2.7.0
Requires-Dist: plotly==5.5.0
Requires-Dist: dash-bootstrap-components>=1.4.0
Requires-Dist: werkzeug==2.0.3
Requires-Dist: ipython>=8.0.0
Requires-Dist: lightgbm>=3.3.0
Requires-Dist: scikit-learn>=1.0.0
Requires-Dist: matplotlib>=3.5.0
Requires-Dist: seaborn>=0.11.0
